yorsent/__init__.py
yorsent/sentiment_model.pkl
yorsent/vectorizer.pkl
yorsent/yorsent.py
yorsent-1.0.dist-info/METADATA
yorsent-1.0.dist-info/WHEEL
yorsent-1.0.dist-info/top_level.txt
yorsent-1.0.dist-info/RECORD
