Metadata-Version: 2.4
Name: yorsent
Version: 1.0
Summary: A Yoruba language model to predict sentiment of Yoruba texts
Author-email: Abeeb Kasaba <kasabaabeeb@gmail.com>
License: Apache-2.0
Project-URL: WebApp, https://yoruba-sentiment-checker.streamlit.app/
Project-URL: Doc, https://www.researchgate.net/publication/395652737_A_Hybrid_Approach_to_Yoruba_Sentiment_Analysis_Integrating_Lexicon-Based_Rules_and_Machine_-_Learning_Models?_sg%5B0%5D=8vJfQsf1VA-UkFECUunrdXKmy893G3WDsVffPwovvelkg8HGHtWK4tN_ofooxMaR1CrSXAXOGysUtTiw0RS4offeIZaDZmQzqPKTvp53.NaquqpMe6e1m_sRPv-hL08O2uW9DuSDuxErVcgZ0X1zZA4z5ePxo-Yna_LNZBqUHKGFUuKes5Vl2m7yeK9GAsA&_tp=eyJjb250ZXh0Ijp7ImZpcnN0UGFnZSI6InByb2ZpbGUiLCJwYWdlIjoicHJvZmlsZSIsInByZXZpb3VzUGFnZSI6InByb2ZpbGUiLCJwb3NpdGlvbiI
Project-URL: Source, https://github.com/Kasaba6330/yoruba-sentiment-checker
Requires-Dist: pandas
Requires-Dist: scikit-learn
Requires-Dist: joblib
